pyroute2/__init__.py
pyroute2/arp.py
pyroute2/common.py
pyroute2/compat.py
pyroute2/conntrack.py
pyroute2/devlink.py
pyroute2/ipset.py
pyroute2/ipvs.py
pyroute2/iwutil.py
pyroute2/minimal.py
pyroute2/process.py
pyroute2/statsd.py
pyroute2/wiset.py
pyroute2/bsd/__init__.py
pyroute2/bsd/util.py
pyroute2/bsd/pf_route/__init__.py
pyroute2/bsd/pf_route/freebsd.py
pyroute2/bsd/pf_route/openbsd.py
pyroute2/bsd/rtmsocket/__init__.py
pyroute2/bsd/rtmsocket/freebsd.py
pyroute2/bsd/rtmsocket/openbsd.py
pyroute2/config/__init__.py
pyroute2/config/asyncio.py
pyroute2/config/eventlet.py
pyroute2/config/log.py
pyroute2/config/test_platform.py
pyroute2/config/version.py
pyroute2/inotify/__init__.py
pyroute2/inotify/inotify_fd.py
pyroute2/inotify/inotify_msg.py
pyroute2/iproute/__init__.py
pyroute2/iproute/bsd.py
pyroute2/iproute/darwin.py
pyroute2/iproute/ipmock.py
pyroute2/iproute/linux.py
pyroute2/iproute/parsers.py
pyroute2/iproute/windows.py
pyroute2/netlink/__init__.py
pyroute2/netlink/buffer.py
pyroute2/netlink/core.py
pyroute2/netlink/coredata.py
pyroute2/netlink/exceptions.py
pyroute2/netlink/marshal.py
pyroute2/netlink/nlsocket.py
pyroute2/netlink/rt_files.py
pyroute2/netlink/devlink/__init__.py
pyroute2/netlink/diag/__init__.py
pyroute2/netlink/diag/ss2.py
pyroute2/netlink/event/__init__.py
pyroute2/netlink/event/acpi_event.py
pyroute2/netlink/event/dquot.py
pyroute2/netlink/event/thermal.py
pyroute2/netlink/generic/__init__.py
pyroute2/netlink/generic/ethtool.py
pyroute2/netlink/generic/ipvs.py
pyroute2/netlink/generic/l2tp.py
pyroute2/netlink/generic/mptcp.py
pyroute2/netlink/generic/wireguard.py
pyroute2/netlink/ipq/__init__.py
pyroute2/netlink/nfnetlink/__init__.py
pyroute2/netlink/nfnetlink/ipset.py
pyroute2/netlink/nfnetlink/nfctsocket.py
pyroute2/netlink/nfnetlink/nftsocket.py
pyroute2/netlink/nl80211/__init__.py
pyroute2/netlink/rtnl/__init__.py
pyroute2/netlink/rtnl/errmsg.py
pyroute2/netlink/rtnl/fibmsg.py
pyroute2/netlink/rtnl/ifaddrmsg.py
pyroute2_minimal-0.9.4.dist-info/licenses/LICENSE
pyroute2_minimal-0.9.4.dist-info/licenses/LICENSE.Apache-2.0
pyroute2_minimal-0.9.4.dist-info/licenses/LICENSE.GPL-2.0-or-later
pyroute2_minimal-0.9.4.dist-info/METADATA
pyroute2_minimal-0.9.4.dist-info/WHEEL
pyroute2_minimal-0.9.4.dist-info/top_level.txt
pyroute2_minimal-0.9.4.dist-info/RECORD
