Metadata-Version: 2.4
Name: pyroute2-minimal
Version: 0.9.4
Summary: Python Netlink library
Author-email: Peter Saveliev <peter@svinota.eu>
License-Expression: GPL-2.0-or-later OR Apache-2.0
Project-URL: Homepage, https://github.com/svinota/pyroute2
Classifier: Programming Language :: Python
Classifier: Topic :: Software Development :: Libraries :: Python Modules
Classifier: Topic :: System :: Networking
Classifier: Topic :: System :: Systems Administration
Classifier: Operating System :: POSIX :: Linux
Classifier: Intended Audience :: Developers
Classifier: Intended Audience :: System Administrators
Classifier: Intended Audience :: Telecommunications Industry
Classifier: Programming Language :: Python :: 3
Classifier: Programming Language :: Python :: 3.9
Classifier: Programming Language :: Python :: 3.10
Classifier: Programming Language :: Python :: 3.11
Classifier: Programming Language :: Python :: 3.12
Classifier: Programming Language :: Python :: 3.13
Classifier: Programming Language :: Python :: 3.14
Classifier: Development Status :: 4 - Beta
Requires-Python: >=3.9
License-File: LICENSE
License-File: LICENSE.Apache-2.0
License-File: LICENSE.GPL-2.0-or-later
Requires-Dist: win_inet_pton; platform_system == "Windows"
Provides-Extra: dev
Requires-Dist: build; extra == "dev"
Requires-Dist: twine; extra == "dev"
Requires-Dist: flake8; extra == "dev"
Requires-Dist: netaddr; extra == "dev"
Requires-Dist: pytest; extra == "dev"
Requires-Dist: pytest-asyncio==0.26.0; extra == "dev"
Requires-Dist: pytest-timeout; extra == "dev"
Requires-Dist: pytest-cov; extra == "dev"
Requires-Dist: pytest-profiling; extra == "dev"
Requires-Dist: pre-commit; extra == "dev"
Requires-Dist: findimports; extra == "dev"
Provides-Extra: docs
Requires-Dist: build; extra == "docs"
Requires-Dist: twine; extra == "docs"
Requires-Dist: aafigure; extra == "docs"
Requires-Dist: sphinx; extra == "docs"
Requires-Dist: sphinx-code-include; extra == "docs"
Requires-Dist: pre-commit; extra == "docs"
Requires-Dist: pytest; extra == "docs"
Requires-Dist: pytest-asyncio==0.26.0; extra == "docs"
Requires-Dist: docutils; extra == "docs"
Provides-Extra: repo
Requires-Dist: nox; extra == "repo"
Requires-Dist: pytest; extra == "repo"
Requires-Dist: pytest-cov; extra == "repo"
Requires-Dist: pytest-html; extra == "repo"
Requires-Dist: pytest-timeout; extra == "repo"
Requires-Dist: setuptools; extra == "repo"
Dynamic: license-file
